{
  "parent": "dungeonsdelight:main/root",
  "criteria": {
    "get_monster_food": {
      "conditions": {
        "items": [
          {
            "items": [
              "dungeonsdelight:spider_tanghulu",
              "dungeonsdelight:cob_n_candy",
              "dungeonsdelight:spider_eye_salmagundi",
              "dungeonsdelight:ghoulash",
              "dungeonsdelight:silverfish_fried_rice",
              "dungeonsdelight:monster_burger",
              "dungeonsdelight:bubblegunk",
              "dungeonsdelight:meef_wellington",
              "dungeonsdelight:gelled_salad",
              "dungeonsdelight:ghast_roll",
              "dungeonsdelight:tokayaki",
              "dungeonsdelight:salt_soaked_stew",
              "dungeonsdelight:soaked_skewer"
            ]
          }
        ]
      },
      "trigger": "minecraft:inventory_changed"
    }
  },
  "display": {
    "announce_to_chat": true,
    "description": {
      "translate": "dungeonsdelight.advancement.get_monster_food.desc"
    },
    "frame": "task",
    "hidden": false,
    "icon": {
      "item": "dungeonsdelight:ghoulash"
    },
    "show_toast": true,
    "title": {
      "translate": "dungeonsdelight.advancement.get_monster_food"
    }
  },
  "requirements": [
    [
      "get_monster_food"
    ]
  ],
  "sends_telemetry_event": true
}