{
  "parent": "dungeonsdelight:main/place_dungeon_stove",
  "criteria": {
    "get_monster_food": {
      "trigger": "minecraft:inventory_changed",
      "conditions": {
        "items": [
          {
            "tag": "dungeonsdelight:monster_foods"
          }
        ]
      }
    }
  },
  "display": {
    "announce_to_chat": true,
    "description": {
      "translate": "dungeonsdelight.advancement.get_monster_food.desc"
    },
    "frame": "task",
    "hidden": false,
    "icon": {
      "item": "dungeonsdelight:gelled_salad"
    },
    "show_toast": true,
    "title": {
      "translate": "dungeonsdelight.advancement.get_monster_food"
    }
  },
  "requirements": [
    [
      "get_monster_food"
    ]
  ],
  "sends_telemetry_event": true
}